hw/main_unit/adc_capture.v
module adc_capture (
  output reg adc_convst,
  output reg adc_sck,
  output reg adc_sdi,
  input   adc_sdo,

  input          clk, // 160MHz, 6.25 ns
  output reg [11:0] adc_ram_addr,
  input   [31:0] adc_ram_rd_data,
  output         adc_ram_we,
  output reg [31:0] adc_ram_wr_data,

  input   [31:0] adc_config_odd,
  input   [31:0] adc_config_even,
  input adc_start,
  input adc_sequence_one
);

//wire [5:0] adc_config [0:1];
//assign adc_config[0][5:0] = adc_config_even[5:0];
//assign adc_config[1][5:0] = adc_config_odd[5:0];
wire [5:0] adc_config;
assign adc_config = ( adc_ram_addr[0] == 1'b1 ) ? adc_config_odd[5:0] : adc_config_even[5:0];
wire start_t_cyc;
assign start_t_cyc = adc_start;
                // tCYC    | Total Cycle Time | 2 μs       (320) /0001 0100 0000/
wire t_wh_conv; // tWHCONV | CONVST High Time | min 20 ns    (4) /0000 0000 0100/
wire t_conv;    // tCONV   | Conversion Time  | max 1.6 μs (256) /0001 0000 0000/

reg [8:0] t_cyc_counter;
always @(posedge clk) begin
  if (start_t_cyc || (t_cyc_counter == 9'd319))
    t_cyc_counter <= 9'b0;
  else
    t_cyc_counter <= t_cyc_counter + 1'b1;
end

always @(posedge clk) begin
  if (start_t_cyc)
    adc_ram_addr <= 9'b0;
  else if (t_cyc_counter == 8'd1)
    adc_ram_addr <= adc_ram_addr + 1'b1;
end

// adc_convst
/* A rising edge at CONVST begins a conversion. For best performance,
ensure that CONVST returns low within 40ns after the conversion starts
or after the conversion ends.*/
always @(posedge clk) begin
  if (t_cyc_counter == 8'd1)
    adc_convst <= 1'b1;
  else if (t_cyc_counter == 8'd7)
    adc_convst <= 1'b0;
end

// adc_sck
always @(posedge clk) begin
  if ((t_cyc_counter[8] == 1'b1) && (t_cyc_counter[7:2] < 6'd12))
    adc_sck <= t_cyc_counter[1];
  else
    adc_sck <= 1'b0;
end

// adc_sdi
always @(posedge clk) begin
  if ((t_cyc_counter[8] == 1'b1) && (t_cyc_counter[7:2] < 6'd6))
    //adc_sdi = adc_config[adc_ram_addr[0]][t_cyc_counter[4:2]];
    adc_sdi <= adc_config[6'd5 - t_cyc_counter[4:2]];
  else
    adc_sdi <= 1'b0;
end

// adc_sdo
reg [11:0] adc_data;
always @(posedge clk) begin
  if ((t_cyc_counter[8] == 1'b1) && (t_cyc_counter[7:2] < 6'd13) && (t_cyc_counter[1:0] == 2'b0))
    adc_data <= {adc_data[10:0],adc_sdo};
end

// wr mem
reg [31:0] adc_ram_rd_data_reg;
always @(posedge clk) begin
  if (t_cyc_counter == 9'd315)
    adc_ram_rd_data_reg <= adc_ram_rd_data;
end
always @(posedge clk) begin
  if (t_cyc_counter == 9'd316)
    adc_ram_wr_data <= adc_ram_rd_data_reg + adc_data;
end
assign adc_ram_we = t_cyc_counter == 9'd317;

endmodule

hw/tb/main_unit__adc_capture__tb.v
// iverilog -y ../main_unit -o adc_capture main_unit__adc_capture__tb.v
// vvp adc_capture
// gtkwave -f main_unit__adc_capture__tb.vcd
`timescale 1ns/10ps

module main_unit__adc_capture__tb;

parameter PERIOD = 6.25; // 160MHz -> 6.25ns, half - 3.125ns :(
parameter DO_CYCLES = 320 * 3;

wire adc_convst;
wire adc_sck;
wire adc_sdi;
wire adc_sdo;
reg clk;

wire [11:0] adc_ram_addr;
reg [31:0] adc_ram_rd_data = 32'h1234;
wire adc_ram_we;
wire [31:0] adc_ram_wr_data;

reg [31:0] adc_config_odd = 32'b101010;
reg [31:0] adc_config_even = 32'b010101;
reg adc_start = 1'b1;
reg adc_sequence_one = 1'b0;

adc_capture adc_capture (
  .adc_convst( adc_convst ),            //output          adc_convst,
  .adc_sck( adc_sck ),                  //output          adc_sck,
  .adc_sdi( adc_sdi ),                  //output          adc_sdi,
  .adc_sdo( adc_sdo ),                  //input           adc_sdo,

  .clk( clk ),                          //input           clk,
  .adc_ram_addr( adc_ram_addr ),        //output  [11:0]  adc_ram_addr,
  .adc_ram_rd_data( adc_ram_rd_data ),  //input   [31:0]  adc_ram_rd_data,
  .adc_ram_we( adc_ram_we ),            //output          adc_ram_we,
  .adc_ram_wr_data( adc_ram_wr_data ),  //output  [31:0]  adc_ram_wr_data,

  .adc_config_odd( adc_config_odd ),    //input   [31:0]  adc_config_odd,
  .adc_config_even( adc_config_even ),  //input   [31:0]  adc_config_even,
  .adc_start( adc_start ),              //input           adc_start,
  .adc_sequence_one( adc_sequence_one ) //input           adc_sequence_one
);

prbs_generate adc_sdo_generate (
  .clk( adc_sck ),
  .prbs( adc_sdo )
);

initial begin
  $dumpfile( "main_unit__adc_capture__tb.vcd" );
  $dumpvars( 1,
    adc_convst,
    adc_sck,
    adc_sdi,
    adc_sdo,

    clk,
    adc_ram_addr,
    adc_ram_rd_data,
    adc_ram_we,
    adc_ram_wr_data,

    adc_config_odd,
    adc_config_even,
    adc_start,
    adc_sequence_one
  );
end

initial begin
  clk = 0;
  forever #( PERIOD / 2 ) clk = ~clk;
end

initial begin
  adc_start = 1'b1;
  #( PERIOD * 13 );
  adc_start = 1'b0;
  repeat ( DO_CYCLES ) @( posedge clk );
  $finish;
end

endmodule

module prbs_generate (
  input clk,
  output prbs
  );

  reg [30:0] prbs_state = 31'h34013FF7;
  wire prbs;
  assign prbs = prbs_state[30];
  always @( posedge clk )
    prbs_state <= { prbs_state, prbs_state[30] ^ prbs_state[27] };

endmodule

hw/tb/main_unit__adc_capture__tb.vcd
$date
	Thu Jan 13 13:07:28 2022
$end
$version
	Icarus Verilog
$end
$timescale
	10ps
$end
$scope module main_unit__adc_capture__tb $end
$var wire 1 ! adc_convst $end
$upscope $end
$scope module main_unit__adc_capture__tb $end
$var wire 1 " adc_sck $end
$upscope $end
$scope module main_unit__adc_capture__tb $end
$var wire 1 # adc_sdi $end
$upscope $end
$scope module main_unit__adc_capture__tb $end
$var wire 1 $ adc_sdo $end
$upscope $end
$scope module main_unit__adc_capture__tb $end
$var reg 1 % clk $end
$upscope $end
$scope module main_unit__adc_capture__tb $end
$var wire 12 & adc_ram_addr [11:0] $end
$upscope $end
$scope module main_unit__adc_capture__tb $end
$var reg 32 ' adc_ram_rd_data [31:0] $end
$upscope $end
$scope module main_unit__adc_capture__tb $end
$var wire 1 ( adc_ram_we $end
$upscope $end
$scope module main_unit__adc_capture__tb $end
$var wire 32 ) adc_ram_wr_data [31:0] $end
$upscope $end
$scope module main_unit__adc_capture__tb $end
$var reg 32 * adc_config_odd [31:0] $end
$upscope $end
$scope module main_unit__adc_capture__tb $end
$var reg 32 + adc_config_even [31:0] $end
$upscope $end
$scope module main_unit__adc_capture__tb $end
$var reg 1 , adc_start $end
$upscope $end
$scope module main_unit__adc_capture__tb $end
$var reg 1 - adc_sequence_one $end
$upscope $end
$enddefinitions $end
#0
$dumpvars
0-
1,
b10101 +
b101010 *
bx )
x(
b1001000110100 '
bx &
0%
0$
x#
x"
x!
$end
#313
0(
b0 &
0"
0#
1%
#626
0%
#939
1%
#1252
0%
#1565
1%
#1878
0%
#2191
1%
#2504
0%
#2817
1%
#3130
0%
#3443
1%
#3756
0%
#4069
1%
#4382
0%
#4695
1%
#5008
0%
#5321
1%
#5634
0%
#5947
1%
#6260
0%
#6573
1%
#6886
0%
#7199
1%
#7512
0%
#7825
1%
#8125
0,
#8138
0%
#8451
1%
#8764
0%
#9077
b1 &
1!
1%
#9390
0%
#9703
1%
#10016
0%
#10329
1%
#10642
0%
#10955
1%
#11268
0%
#11581
1%
#11894
0%
#12207
1%
#12520
0%
#12833
1%
#13146
0%
#13459
0!
1%
#13772
0%
#14085
1%
#14398
0%
#14711
1%
#15024
0%
#15337
1%
#15650
0%
#15963
1%
#16276
0%
#16589
1%
#16902
0%
#17215
1%
#17528
0%
#17841
1%
#18154
0%
#18467
1%
#18780
0%
#19093
1%
#19406
0%
#19719
1%
#20032
0%
#20345
1%
#20658
0%
#20971
1%
#21284
0%
#21597
1%
#21910
0%
#22223
1%
#22536
0%
#22849
1%
#23162
0%
#23475
1%
#23788
0%
#24101
1%
#24414
0%
#24727
1%
#25040
0%
#25353
1%
#25666
0%
#25979
1%
#26292
0%
#26605
1%
#26918
0%
#27231
1%
#27544
0%
#27857
1%
#28170
0%
#28483
1%
#28796
0%
#29109
1%
#29422
0%
#29735
1%
#30048
0%
#30361
1%
#30674
0%
#30987
1%
#31300
0%
#31613
1%
#31926
0%
#32239
1%
#32552
0%
#32865
1%
#33178
0%
#33491
1%
#33804
0%
#34117
1%
#34430
0%
#34743
1%
#35056
0%
#35369
1%
#35682
0%
#35995
1%
#36308
0%
#36621
1%
#36934
0%
#37247
1%
#37560
0%
#37873
1%
#38186
0%
#38499
1%
#38812
0%
#39125
1%
#39438
0%
#39751
1%
#40064
0%
#40377
1%
#40690
0%
#41003
1%
#41316
0%
#41629
1%
#41942
0%
#42255
1%
#42568
0%
#42881
1%
#43194
0%
#43507
1%
#43820
0%
#44133
1%
#44446
0%
#44759
1%
#45072
0%
#45385
1%
#45698
0%
#46011
1%
#46324
0%
#46637
1%
#46950
0%
#47263
1%
#47576
0%
#47889
1%
#48202
0%
#48515
1%
#48828
0%
#49141
1%
#49454
0%
#49767
1%
#50080
0%
#50393
1%
#50706
0%
#51019
1%
#51332
0%
#51645
1%
#51958
0%
#52271
1%
#52584
0%
#52897
1%
#53210
0%
#53523
1%
#53836
0%
#54149
1%
#54462
0%
#54775
1%
#55088
0%
#55401
1%
#55714
0%
#56027
1%
#56340
0%
#56653
1%
#56966
0%
#57279
1%
#57592
0%
#57905
1%
#58218
0%
#58531
1%
#58844
0%
#59157
1%
#59470
0%
#59783
1%
#60096
0%
#60409
1%
#60722
0%
#61035
1%
#61348
0%
#61661
1%
#61974
0%
#62287
1%
#62600
0%
#62913
1%
#63226
0%
#63539
1%
#63852
0%
#64165
1%
#64478
0%
#64791
1%
#65104
0%
#65417
1%
#65730
0%
#66043
1%
#66356
0%
#66669
1%
#66982
0%
#67295
1%
#67608
0%
#67921
1%
#68234
0%
#68547
1%
#68860
0%
#69173
1%
#69486
0%
#69799
1%
#70112
0%
#70425
1%
#70738
0%
#71051
1%
#71364
0%
#71677
1%
#71990
0%
#72303
1%
#72616
0%
#72929
1%
#73242
0%
#73555
1%
#73868
0%
#74181
1%
#74494
0%
#74807
1%
#75120
0%
#75433
1%
#75746
0%
#76059
1%
#76372
0%
#76685
1%
#76998
0%
#77311
1%
#77624
0%
#77937
1%
#78250
0%
#78563
1%
#78876
0%
#79189
1%
#79502
0%
#79815
1%
#80128
0%
#80441
1%
#80754
0%
#81067
1%
#81380
0%
#81693
1%
#82006
0%
#82319
1%
#82632
0%
#82945
1%
#83258
0%
#83571
1%
#83884
0%
#84197
1%
#84510
0%
#84823
1%
#85136
0%
#85449
1%
#85762
0%
#86075
1%
#86388
0%
#86701
1%
#87014
0%
#87327
1%
#87640
0%
#87953
1%
#88266
0%
#88579
1%
#88892
0%
#89205
1%
#89518
0%
#89831
1%
#90144
0%
#90457
1%
#90770
0%
#91083
1%
#91396
0%
#91709
1%
#92022
0%
#92335
1%
#92648
0%
#92961
1%
#93274
0%
#93587
1%
#93900
0%
#94213
1%
#94526
0%
#94839
1%
#95152
0%
#95465
1%
#95778
0%
#96091
1%
#96404
0%
#96717
1%
#97030
0%
#97343
1%
#97656
0%
#97969
1%
#98282
0%
#98595
1%
#98908
0%
#99221
1%
#99534
0%
#99847
1%
#100160
0%
#100473
1%
#100786
0%
#101099
1%
#101412
0%
#101725
1%
#102038
0%
#102351
1%
#102664
0%
#102977
1%
#103290
0%
#103603
1%
#103916
0%
#104229
1%
#104542
0%
#104855
1%
#105168
0%
#105481
1%
#105794
0%
#106107
1%
#106420
0%
#106733
1%
#107046
0%
#107359
1%
#107672
0%
#107985
1%
#108298
0%
#108611
1%
#108924
0%
#109237
1%
#109550
0%
#109863
1%
#110176
0%
#110489
1%
#110802
0%
#111115
1%
#111428
0%
#111741
1%
#112054
0%
#112367
1%
#112680
0%
#112993
1%
#113306
0%
#113619
1%
#113932
0%
#114245
1%
#114558
0%
#114871
1%
#115184
0%
#115497
1%
#115810
0%
#116123
1%
#116436
0%
#116749
1%
#117062
0%
#117375
1%
#117688
0%
#118001
1%
#118314
0%
#118627
1%
#118940
0%
#119253
1%
#119566
0%
#119879
1%
#120192
0%
#120505
1%
#120818
0%
#121131
1%
#121444
0%
#121757
1%
#122070
0%
#122383
1%
#122696
0%
#123009
1%
#123322
0%
#123635
1%
#123948
0%
#124261
1%
#124574
0%
#124887
1%
#125200
0%
#125513
1%
#125826
0%
#126139
1%
#126452
0%
#126765
1%
#127078
0%
#127391
1%
#127704
0%
#128017
1%
#128330
0%
#128643
1%
#128956
0%
#129269
1%
#129582
0%
#129895
1%
#130208
0%
#130521
1%
#130834
0%
#131147
1%
#131460
0%
#131773
1%
#132086
0%
#132399
1%
#132712
0%
#133025
1%
#133338
0%
#133651
1%
#133964
0%
#134277
1%
#134590
0%
#134903
1%
#135216
0%
#135529
1%
#135842
0%
#136155
1%
#136468
0%
#136781
1%
#137094
0%
#137407
1%
#137720
0%
#138033
1%
#138346
0%
#138659
1%
#138972
0%
#139285
1%
#139598
0%
#139911
1%
#140224
0%
#140537
1%
#140850
0%
#141163
1%
#141476
0%
#141789
1%
#142102
0%
#142415
1%
#142728
0%
#143041
1%
#143354
0%
#143667
1%
#143980
0%
#144293
1%
#144606
0%
#144919
1%
#145232
0%
#145545
1%
#145858
0%
#146171
1%
#146484
0%
#146797
1%
#147110
0%
#147423
1%
#147736
0%
#148049
1%
#148362
0%
#148675
1%
#148988
0%
#149301
1%
#149614
0%
#149927
1%
#150240
0%
#150553
1%
#150866
0%
#151179
1%
#151492
0%
#151805
1%
#152118
0%
#152431
1%
#152744
0%
#153057
1%
#153370
0%
#153683
1%
#153996
0%
#154309
1%
#154622
0%
#154935
1%
#155248
0%
#155561
1%
#155874
0%
#156187
1%
#156500
0%
#156813
1%
#157126
0%
#157439
1%
#157752
0%
#158065
1%
#158378
0%
#158691
1%
#159004
0%
#159317
1%
#159630
0%
#159943
1%
#160256
0%
#160569
1%
#160882
0%
#161195
1%
#161508
0%
#161821
1%
#162134
0%
#162447
1%
#162760
0%
#163073
1%
#163386
0%
#163699
1%
#164012
0%
#164325
1%
#164638
0%
#164951
1%
#165264
0%
#165577
1%
#165890
0%
#166203
1%
#166516
0%
#166829
1%
#167142
0%
#167455
1%
#167768
0%
#168081
1%
#168394
0%
#168707
1%
#169020
0%
#169333
1%
#169646
0%
#169959
1$
1"
1%
#170272
0%
#170585
1%
#170898
0%
#171211
1#
0"
1%
#171524
0%
#171837
1%
#172150
0%
#172463
1"
1%
#172776
0%
#173089
1%
#173402
0%
#173715
0#
0"
1%
#174028
0%
#174341
1%
#174654
0%
#174967
0$
1"
1%
#175280
0%
#175593
1%
#175906
0%
#176219
1#
0"
1%
#176532
0%
#176845
1%
#177158
0%
#177471
1$
1"
1%
#177784
0%
#178097
1%
#178410
0%
#178723
0#
0"
1%
#179036
0%
#179349
1%
#179662
0%
#179975
0$
1"
1%
#180288
0%
#180601
1%
#180914
0%
#181227
1#
0"
1%
#181540
0%
#181853
1%
#182166
0%
#182479
1"
1%
#182792
0%
#183105
1%
#183418
0%
#183731
0#
0"
1%
#184044
0%
#184357
1%
#184670
0%
#184983
1"
1%
#185296
0%
#185609
1%
#185922
0%
#186235
0"
1%
#186548
0%
#186861
1%
#187174
0%
#187487
1"
1%
#187800
0%
#188113
1%
#188426
0%
#188739
0"
1%
#189052
0%
#189365
1%
#189678
0%
#189991
1"
1%
#190304
0%
#190617
1%
#190930
0%
#191243
0"
1%
#191556
0%
#191869
1%
#192182
0%
#192495
1"
1%
#192808
0%
#193121
1%
#193434
0%
#193747
0"
1%
#194060
0%
#194373
1%
#194686
0%
#194999
1"
1%
#195312
0%
#195625
1%
#195938
0%
#196251
0"
1%
#196564
0%
#196877
1%
#197190
0%
#197503
1"
1%
#197816
0%
#198129
1%
#198442
0%
#198755
0"
1%
#199068
0%
#199381
1%
#199694
0%
#200007
1%
#200320
0%
#200633
1%
#200946
0%
#201259
1%
#201572
0%
#201885
1%
#202198
0%
#202511
1%
#202824
0%
#203137
1%
#203450
0%
#203763
1%
#204076
0%
#204389
1%
#204702
0%
#205015
1%
#205328
0%
#205641
1%
#205954
0%
#206267
b1100010110100 )
1(
1%
#206580
0%
#206893
0(
1%
#207206
0%
#207519
1%
#207832
0%
#208145
1%
#208458
0%
#208771
1%
#209084
0%
#209397
1%
#209710
0%
#210023
1!
b10 &
1%
#210336
0%
#210649
1%
#210962
0%
#211275
1%
#211588
0%
#211901
1%
#212214
0%
#212527
1%
#212840
0%
#213153
1%
#213466
0%
#213779
1%
#214092
0%
#214405
0!
1%
