hw/main_unit/adc_capture.v
module adc_capture (
  output reg adc_convst,
  output reg adc_sck,
  output reg adc_sdi,
  input   adc_sdo,

  input          clk, // 160MHz, 6.25 ns
  output reg [11:0] adc_ram_addr,
  input   [31:0] adc_ram_rd_data,
  output         adc_ram_we,
  output reg [31:0] adc_ram_wr_data,

  input   [31:0] adc_config_odd,
  input   [31:0] adc_config_even,
  input adc_start,
  input adc_sequence_one
);

//wire [5:0] adc_config [0:1];
//assign adc_config[0][5:0] = adc_config_even[5:0];
//assign adc_config[1][5:0] = adc_config_odd[5:0];
wire [5:0] adc_config;
assign adc_config = ( adc_ram_addr[0] == 1'b1 ) ? adc_config_odd[5:0] : adc_config_even[5:0];
wire start_t_cyc;
assign start_t_cyc = adc_start;
                // tCYC    | Total Cycle Time | 2 μs       (320) /0001 0100 0000/
wire t_wh_conv; // tWHCONV | CONVST High Time | min 20 ns    (4) /0000 0000 0100/
wire t_conv;    // tCONV   | Conversion Time  | max 1.6 μs (256) /0001 0000 0000/

reg [8:0] t_cyc_counter;
always @(posedge clk) begin
  if (start_t_cyc || (t_cyc_counter == 9'd320))
    t_cyc_counter <= 9'b0;
  else
    t_cyc_counter <= t_cyc_counter + 1'b1;
end

always @(posedge clk) begin
  if (start_t_cyc)
    adc_ram_addr <= 9'b0;
  else if (t_cyc_counter == 8'd1)
    adc_ram_addr <= adc_ram_addr + 1'b1;
end

// adc_convst
/* A rising edge at CONVST begins a conversion. For best performance,
ensure that CONVST returns low within 40ns after the conversion starts
or after the conversion ends.*/
always @(posedge clk) begin
  if (t_cyc_counter == 8'd1)
    adc_convst <= 1'b1;
  else if (t_cyc_counter == 8'd8)
    adc_convst <= 1'b0;
end

// adc_sck
always @(posedge clk) begin
  if ((t_cyc_counter[8] == 1'b1) && (t_cyc_counter[7:2] < 6'd12))
    adc_sck <= t_cyc_counter[1];
  else
    adc_sck <= 1'b0;
end

// adc_sdi
always @(posedge clk) begin
  if ((t_cyc_counter[8] == 1'b1) && (t_cyc_counter[7:2] < 6'd6))
    //adc_sdi = adc_config[adc_ram_addr[0]][t_cyc_counter[4:2]];
    adc_sdi <= adc_config[t_cyc_counter[4:2]];
  else
    adc_sdi <= 1'b0;
end

// adc_sdo
reg [11:0] adc_data;
always @(posedge clk) begin
  if ((t_cyc_counter[8] == 1'b1) && (t_cyc_counter[7:2] < 6'd12) && (t_cyc_counter[1:0] == 2'b0))
    adc_data <= {adc_data[10:0],adc_sdo};
end

// wr mem
reg [31:0] adc_ram_rd_data_reg;
always @(posedge clk) begin
  if (t_cyc_counter == 9'd315)
    adc_ram_rd_data_reg <= adc_ram_rd_data;
end
always @(posedge clk) begin
  if (t_cyc_counter == 9'd316)
    adc_ram_wr_data <= adc_ram_rd_data_reg + adc_data;
end
assign adc_ram_we = t_cyc_counter == 9'd317;

endmodule

hw/tb/main_unit__adc_capture__tb.v
// iverilog -y ../main_unit -o adc_capture main_unit__adc_capture__tb.v
// vvp adc_capture
// gtkwave -f main_unit__adc_capture__tb.vcd
`timescale 1 ns / 10 ps

module main_unit__adc_capture__tb;

parameter PERIOD = 6.25; // 160MHz -> 6.25ns
parameter DO_CYCLES = 320*3;

wire adc_convst;
wire adc_sck;
wire adc_sdi;
reg adc_sdo = 1'b1;
reg clk;

wire [11:0] adc_ram_addr;
reg [31:0] adc_ram_rd_data = 32'h1234;
wire adc_ram_we;
wire [31:0] adc_ram_wr_data;

reg [31:0] adc_config_odd = 32'b101010;
reg [31:0] adc_config_even = 32'b010101;
reg adc_start = 1'b1;
reg adc_sequence_one = 1'b0;


adc_capture adc_capture (
  .adc_convst(adc_convst),//output  adc_convst,
  .adc_sck(adc_sck),//output  adc_sck,
  .adc_sdi(adc_sdi),//output  adc_sdi,
  .adc_sdo(adc_sdo),//input   adc_sdo,

  .clk(clk),//input          clk,
  .adc_ram_addr(adc_ram_addr),//output  [11:0] adc_ram_addr,
  .adc_ram_rd_data(adc_ram_rd_data),//input   [31:0] adc_ram_rd_data,
  .adc_ram_we(adc_ram_we),//output         adc_ram_we,
  .adc_ram_wr_data(adc_ram_wr_data),//output  [31:0] adc_ram_wr_data,

  .adc_config_odd(adc_config_odd),//input   [31:0] adc_config_odd,
  .adc_config_even(adc_config_even),//input   [31:0] adc_config_even,
  .adc_start(adc_start),//input adc_start
  .adc_sequence_one(adc_sequence_one)//input adc_sequence_one
);

initial begin
  $dumpfile("main_unit__adc_capture__tb.vcd");
  $dumpvars(0, adc_capture);
end

initial begin
  clk = 0;
  forever #(PERIOD/2) clk = ~clk;
end

initial begin
  adc_start = 1'b1;
  #(PERIOD*13);
  adc_start = 1'b0;
  repeat (DO_CYCLES) @(negedge clk);
  $finish;
end

endmodule

hw/tb/main_unit__adc_capture__tb.vcd
$date
	Wed Jan 12 14:10:57 2022
$end
$version
	Icarus Verilog
$end
$timescale
	10ps
$end
$scope module main_unit__adc_capture__tb $end
$scope module adc_capture $end
$var wire 32 ! adc_config_even [31:0] $end
$var wire 32 " adc_config_odd [31:0] $end
$var wire 32 # adc_ram_rd_data [31:0] $end
$var wire 1 $ adc_sdo $end
$var wire 1 % adc_sequence_one $end
$var wire 1 & adc_start $end
$var wire 1 ' clk $end
$var wire 1 ( start_t_cyc $end
$var wire 1 ) adc_ram_we $end
$var wire 6 * adc_config [5:0] $end
$var reg 1 + adc_convst $end
$var reg 12 , adc_data [11:0] $end
$var reg 12 - adc_ram_addr [11:0] $end
$var reg 32 . adc_ram_rd_data_reg [31:0] $end
$var reg 32 / adc_ram_wr_data [31:0] $end
$var reg 1 0 adc_sck $end
$var reg 1 1 adc_sdi $end
$var reg 9 2 t_cyc_counter [8:0] $end
$upscope $end
$upscope $end
$enddefinitions $end
#0
$dumpvars
bx 2
x1
x0
bx /
bx .
bx -
bx ,
x+
bx *
x)
1(
0'
1&
0%
1$
b1001000110100 #
b101010 "
b10101 !
$end
#313
b10101 *
0)
b0 2
b0 -
00
01
1'
#626
0'
#939
1'
#1252
0'
#1565
1'
#1878
0'
#2191
1'
#2504
0'
#2817
1'
#3130
0'
#3443
1'
#3756
0'
#4069
1'
#4382
0'
#4695
1'
#5008
0'
#5321
1'
#5634
0'
#5947
1'
#6260
0'
#6573
1'
#6886
0'
#7199
1'
#7512
0'
#7825
1'
#8125
0(
0&
#8138
0'
#8451
b1 2
1'
#8764
0'
#9077
b101010 *
b10 2
b1 -
1+
1'
#9390
0'
#9703
b11 2
1'
#10016
0'
#10329
b100 2
1'
#10642
0'
#10955
b101 2
1'
#11268
0'
#11581
b110 2
1'
#11894
0'
#12207
b111 2
1'
#12520
0'
#12833
b1000 2
1'
#13146
0'
#13459
0+
b1001 2
1'
#13772
0'
#14085
b1010 2
1'
#14398
0'
#14711
b1011 2
1'
#15024
0'
#15337
b1100 2
1'
#15650
0'
#15963
b1101 2
1'
#16276
0'
#16589
b1110 2
1'
#16902
0'
#17215
b1111 2
1'
#17528
0'
#17841
b10000 2
1'
#18154
0'
#18467
b10001 2
1'
#18780
0'
#19093
b10010 2
1'
#19406
0'
#19719
b10011 2
1'
#20032
0'
#20345
b10100 2
1'
#20658
0'
#20971
b10101 2
1'
#21284
0'
#21597
b10110 2
1'
#21910
0'
#22223
b10111 2
1'
#22536
0'
#22849
b11000 2
1'
#23162
0'
#23475
b11001 2
1'
#23788
0'
#24101
b11010 2
1'
#24414
0'
#24727
b11011 2
1'
#25040
0'
#25353
b11100 2
1'
#25666
0'
#25979
b11101 2
1'
#26292
0'
#26605
b11110 2
1'
#26918
0'
#27231
b11111 2
1'
#27544
0'
#27857
b100000 2
1'
#28170
0'
#28483
b100001 2
1'
#28796
0'
#29109
b100010 2
1'
#29422
0'
#29735
b100011 2
1'
#30048
0'
#30361
b100100 2
1'
#30674
0'
#30987
b100101 2
1'
#31300
0'
#31613
b100110 2
1'
#31926
0'
#32239
b100111 2
1'
#32552
0'
#32865
b101000 2
1'
#33178
0'
#33491
b101001 2
1'
#33804
0'
#34117
b101010 2
1'
#34430
0'
#34743
b101011 2
1'
#35056
0'
#35369
b101100 2
1'
#35682
0'
#35995
b101101 2
1'
#36308
0'
#36621
b101110 2
1'
#36934
0'
#37247
b101111 2
1'
#37560
0'
#37873
b110000 2
1'
#38186
0'
#38499
b110001 2
1'
#38812
0'
#39125
b110010 2
1'
#39438
0'
#39751
b110011 2
1'
#40064
0'
#40377
b110100 2
1'
#40690
0'
#41003
b110101 2
1'
#41316
0'
#41629
b110110 2
1'
#41942
0'
#42255
b110111 2
1'
#42568
0'
#42881
b111000 2
1'
#43194
0'
#43507
b111001 2
1'
#43820
0'
#44133
b111010 2
1'
#44446
0'
#44759
b111011 2
1'
#45072
0'
#45385
b111100 2
1'
#45698
0'
#46011
b111101 2
1'
#46324
0'
#46637
b111110 2
1'
#46950
0'
#47263
b111111 2
1'
#47576
0'
#47889
b1000000 2
1'
#48202
0'
#48515
b1000001 2
1'
#48828
0'
#49141
b1000010 2
1'
#49454
0'
#49767
b1000011 2
1'
#50080
0'
#50393
b1000100 2
1'
#50706
0'
#51019
b1000101 2
1'
#51332
0'
#51645
b1000110 2
1'
#51958
0'
#52271
b1000111 2
1'
#52584
0'
#52897
b1001000 2
1'
#53210
0'
#53523
b1001001 2
1'
#53836
0'
#54149
b1001010 2
1'
#54462
0'
#54775
b1001011 2
1'
#55088
0'
#55401
b1001100 2
1'
#55714
0'
#56027
b1001101 2
1'
#56340
0'
#56653
b1001110 2
1'
#56966
0'
#57279
b1001111 2
1'
#57592
0'
#57905
b1010000 2
1'
#58218
0'
#58531
b1010001 2
1'
#58844
0'
#59157
b1010010 2
1'
#59470
0'
#59783
b1010011 2
1'
#60096
0'
#60409
b1010100 2
1'
#60722
0'
#61035
b1010101 2
1'
#61348
0'
#61661
b1010110 2
1'
#61974
0'
#62287
b1010111 2
1'
#62600
0'
#62913
b1011000 2
1'
#63226
0'
#63539
b1011001 2
1'
#63852
0'
#64165
b1011010 2
1'
#64478
0'
#64791
b1011011 2
1'
#65104
0'
#65417
b1011100 2
1'
#65730
0'
#66043
b1011101 2
1'
#66356
0'
#66669
b1011110 2
1'
#66982
0'
#67295
b1011111 2
1'
#67608
0'
#67921
b1100000 2
1'
#68234
0'
#68547
b1100001 2
1'
#68860
0'
#69173
b1100010 2
1'
#69486
0'
#69799
b1100011 2
1'
#70112
0'
#70425
b1100100 2
1'
#70738
0'
#71051
b1100101 2
1'
#71364
0'
#71677
b1100110 2
1'
#71990
0'
#72303
b1100111 2
1'
#72616
0'
#72929
b1101000 2
1'
#73242
0'
#73555
b1101001 2
1'
#73868
0'
#74181
b1101010 2
1'
#74494
0'
#74807
b1101011 2
1'
#75120
0'
#75433
b1101100 2
1'
#75746
0'
#76059
b1101101 2
1'
#76372
0'
#76685
b1101110 2
1'
#76998
0'
#77311
b1101111 2
1'
#77624
0'
#77937
b1110000 2
1'
#78250
0'
#78563
b1110001 2
1'
#78876
0'
#79189
b1110010 2
1'
#79502
0'
#79815
b1110011 2
1'
#80128
0'
#80441
b1110100 2
1'
#80754
0'
#81067
b1110101 2
1'
#81380
0'
#81693
b1110110 2
1'
#82006
0'
#82319
b1110111 2
1'
#82632
0'
#82945
b1111000 2
1'
#83258
0'
#83571
b1111001 2
1'
#83884
0'
#84197
b1111010 2
1'
#84510
0'
#84823
b1111011 2
1'
#85136
0'
#85449
b1111100 2
1'
#85762
0'
#86075
b1111101 2
1'
#86388
0'
#86701
b1111110 2
1'
#87014
0'
#87327
b1111111 2
1'
#87640
0'
#87953
b10000000 2
1'
#88266
0'
#88579
b10000001 2
1'
#88892
0'
#89205
b10000010 2
1'
#89518
0'
#89831
b10000011 2
1'
#90144
0'
#90457
b10000100 2
1'
#90770
0'
#91083
b10000101 2
1'
#91396
0'
#91709
b10000110 2
1'
#92022
0'
#92335
b10000111 2
1'
#92648
0'
#92961
b10001000 2
1'
#93274
0'
#93587
b10001001 2
1'
#93900
0'
#94213
b10001010 2
1'
#94526
0'
#94839
b10001011 2
1'
#95152
0'
#95465
b10001100 2
1'
#95778
0'
#96091
b10001101 2
1'
#96404
0'
#96717
b10001110 2
1'
#97030
0'
#97343
b10001111 2
1'
#97656
0'
#97969
b10010000 2
1'
#98282
0'
#98595
b10010001 2
1'
#98908
0'
#99221
b10010010 2
1'
#99534
0'
#99847
b10010011 2
1'
#100160
0'
#100473
b10010100 2
1'
#100786
0'
#101099
b10010101 2
1'
#101412
0'
#101725
b10010110 2
1'
#102038
0'
#102351
b10010111 2
1'
#102664
0'
#102977
b10011000 2
1'
#103290
0'
#103603
b10011001 2
1'
#103916
0'
#104229
b10011010 2
1'
#104542
0'
#104855
b10011011 2
1'
#105168
0'
#105481
b10011100 2
1'
#105794
0'
#106107
b10011101 2
1'
#106420
0'
#106733
b10011110 2
1'
#107046
0'
#107359
b10011111 2
1'
#107672
0'
#107985
b10100000 2
1'
#108298
0'
#108611
b10100001 2
1'
#108924
0'
#109237
b10100010 2
1'
#109550
0'
#109863
b10100011 2
1'
#110176
0'
#110489
b10100100 2
1'
#110802
0'
#111115
b10100101 2
1'
#111428
0'
#111741
b10100110 2
1'
#112054
0'
#112367
b10100111 2
1'
#112680
0'
#112993
b10101000 2
1'
#113306
0'
#113619
b10101001 2
1'
#113932
0'
#114245
b10101010 2
1'
#114558
0'
#114871
b10101011 2
1'
#115184
0'
#115497
b10101100 2
1'
#115810
0'
#116123
b10101101 2
1'
#116436
0'
#116749
b10101110 2
1'
#117062
0'
#117375
b10101111 2
1'
#117688
0'
#118001
b10110000 2
1'
#118314
0'
#118627
b10110001 2
1'
#118940
0'
#119253
b10110010 2
1'
#119566
0'
#119879
b10110011 2
1'
#120192
0'
#120505
b10110100 2
1'
#120818
0'
#121131
b10110101 2
1'
#121444
0'
#121757
b10110110 2
1'
#122070
0'
#122383
b10110111 2
1'
#122696
0'
#123009
b10111000 2
1'
#123322
0'
#123635
b10111001 2
1'
#123948
0'
#124261
b10111010 2
1'
#124574
0'
#124887
b10111011 2
1'
#125200
0'
#125513
b10111100 2
1'
#125826
0'
#126139
b10111101 2
1'
#126452
0'
#126765
b10111110 2
1'
#127078
0'
#127391
b10111111 2
1'
#127704
0'
#128017
b11000000 2
1'
#128330
0'
#128643
b11000001 2
1'
#128956
0'
#129269
b11000010 2
1'
#129582
0'
#129895
b11000011 2
1'
#130208
0'
#130521
b11000100 2
1'
#130834
0'
#131147
b11000101 2
1'
#131460
0'
#131773
b11000110 2
1'
#132086
0'
#132399
b11000111 2
1'
#132712
0'
#133025
b11001000 2
1'
#133338
0'
#133651
b11001001 2
1'
#133964
0'
#134277
b11001010 2
1'
#134590
0'
#134903
b11001011 2
1'
#135216
0'
#135529
b11001100 2
1'
#135842
0'
#136155
b11001101 2
1'
#136468
0'
#136781
b11001110 2
1'
#137094
0'
#137407
b11001111 2
1'
#137720
0'
#138033
b11010000 2
1'
#138346
0'
#138659
b11010001 2
1'
#138972
0'
#139285
b11010010 2
1'
#139598
0'
#139911
b11010011 2
1'
#140224
0'
#140537
b11010100 2
1'
#140850
0'
#141163
b11010101 2
1'
#141476
0'
#141789
b11010110 2
1'
#142102
0'
#142415
b11010111 2
1'
#142728
0'
#143041
b11011000 2
1'
#143354
0'
#143667
b11011001 2
1'
#143980
0'
#144293
b11011010 2
1'
#144606
0'
#144919
b11011011 2
1'
#145232
0'
#145545
b11011100 2
1'
#145858
0'
#146171
b11011101 2
1'
#146484
0'
#146797
b11011110 2
1'
#147110
0'
#147423
b11011111 2
1'
#147736
0'
#148049
b11100000 2
1'
#148362
0'
#148675
b11100001 2
1'
#148988
0'
#149301
b11100010 2
1'
#149614
0'
#149927
b11100011 2
1'
#150240
0'
#150553
b11100100 2
1'
#150866
0'
#151179
b11100101 2
1'
#151492
0'
#151805
b11100110 2
1'
#152118
0'
#152431
b11100111 2
1'
#152744
0'
#153057
b11101000 2
1'
#153370
0'
#153683
b11101001 2
1'
#153996
0'
#154309
b11101010 2
1'
#154622
0'
#154935
b11101011 2
1'
#155248
0'
#155561
b11101100 2
1'
#155874
0'
#156187
b11101101 2
1'
#156500
0'
#156813
b11101110 2
1'
#157126
0'
#157439
b11101111 2
1'
#157752
0'
#158065
b11110000 2
1'
#158378
0'
#158691
b11110001 2
1'
#159004
0'
#159317
b11110010 2
1'
#159630
0'
#159943
b11110011 2
1'
#160256
0'
#160569
b11110100 2
1'
#160882
0'
#161195
b11110101 2
1'
#161508
0'
#161821
b11110110 2
1'
#162134
0'
#162447
b11110111 2
1'
#162760
0'
#163073
b11111000 2
1'
#163386
0'
#163699
b11111001 2
1'
#164012
0'
#164325
b11111010 2
1'
#164638
0'
#164951
b11111011 2
1'
#165264
0'
#165577
b11111100 2
1'
#165890
0'
#166203
b11111101 2
1'
#166516
0'
#166829
b11111110 2
1'
#167142
0'
#167455
b11111111 2
1'
#167768
0'
#168081
b100000000 2
1'
#168394
0'
#168707
bx1 ,
b100000001 2
1'
#169020
0'
#169333
b100000010 2
1'
#169646
0'
#169959
10
b100000011 2
1'
#170272
0'
#170585
b100000100 2
1'
#170898
0'
#171211
bx11 ,
11
00
b100000101 2
1'
#171524
0'
#171837
b100000110 2
1'
#172150
0'
#172463
10
b100000111 2
1'
#172776
0'
#173089
b100001000 2
1'
#173402
0'
#173715
bx111 ,
01
00
b100001001 2
1'
#174028
0'
#174341
b100001010 2
1'
#174654
0'
#174967
10
b100001011 2
1'
#175280
0'
#175593
b100001100 2
1'
#175906
0'
#176219
bx1111 ,
11
00
b100001101 2
1'
#176532
0'
#176845
b100001110 2
1'
#177158
0'
#177471
10
b100001111 2
1'
#177784
0'
#178097
b100010000 2
1'
#178410
0'
#178723
bx11111 ,
01
00
b100010001 2
1'
#179036
0'
#179349
b100010010 2
1'
#179662
0'
#179975
10
b100010011 2
1'
#180288
0'
#180601
b100010100 2
1'
#180914
0'
#181227
bx111111 ,
11
00
b100010101 2
1'
#181540
0'
#181853
b100010110 2
1'
#182166
0'
#182479
10
b100010111 2
1'
#182792
0'
#183105
b100011000 2
1'
#183418
0'
#183731
bx1111111 ,
01
00
b100011001 2
1'
#184044
0'
#184357
b100011010 2
1'
#184670
0'
#184983
10
b100011011 2
1'
#185296
0'
#185609
b100011100 2
1'
#185922
0'
#186235
bx11111111 ,
00
b100011101 2
1'
#186548
0'
#186861
b100011110 2
1'
#187174
0'
#187487
10
b100011111 2
1'
#187800
0'
#188113
b100100000 2
1'
#188426
0'
#188739
bx111111111 ,
00
b100100001 2
1'
#189052
0'
#189365
b100100010 2
1'
#189678
0'
#189991
10
b100100011 2
1'
#190304
0'
#190617
b100100100 2
1'
#190930
0'
#191243
bx1111111111 ,
00
b100100101 2
1'
#191556
0'
#191869
b100100110 2
1'
#192182
0'
#192495
10
b100100111 2
1'
#192808
0'
#193121
b100101000 2
1'
#193434
0'
#193747
bx11111111111 ,
00
b100101001 2
1'
#194060
0'
#194373
b100101010 2
1'
#194686
0'
#194999
10
b100101011 2
1'
#195312
0'
#195625
b100101100 2
1'
#195938
0'
#196251
b111111111111 ,
00
b100101101 2
1'
#196564
0'
#196877
b100101110 2
1'
#197190
0'
#197503
10
b100101111 2
1'
#197816
0'
#198129
b100110000 2
1'
#198442
0'
#198755
00
b100110001 2
1'
#199068
0'
#199381
b100110010 2
1'
#199694
0'
#200007
b100110011 2
1'
#200320
0'
#200633
b100110100 2
1'
#200946
0'
#201259
b100110101 2
1'
#201572
0'
#201885
b100110110 2
1'
#202198
0'
#202511
b100110111 2
1'
#202824
0'
#203137
b100111000 2
1'
#203450
0'
#203763
b100111001 2
1'
#204076
0'
#204389
b100111010 2
1'
#204702
0'
#205015
b100111011 2
1'
#205328
0'
#205641
b100111100 2
b1001000110100 .
1'
#205954
0'
#206267
b10001000110011 /
1)
b100111101 2
1'
#206580
0'
#206893
0)
b100111110 2
1'
#207206
0'
#207519
b100111111 2
1'
#207832
0'
#208145
b101000000 2
1'
#208458
0'
#208771
b0 2
1'
#209084
0'
#209397
b1 2
1'
#209710
0'
#210023
b10101 *
1+
b10 -
b10 2
1'
#210336
0'
#210649
b11 2
1'
#210962
0'
#211275
b100 2
1'
#211588
0'
#211901
b101 2
1'
#212214
0'
#212527
b110 2
1'
#212840
0'
#213153
b111 2
1'
#213466
0'
#213779
b1000 2
1'
#214092
0'
#214405
b1001 2
0+
1'
#214718
0'
#215031
b1010 2
1'
#215344
0'
#215657
b1011 2
1'
#215970
0'
#216283
b1100 2
1'
#216596
0'
#216909
b1101 2
1'
#217222
0'
#217535
b1110 2
1'
#217848
0'
#218161
b1111 2
1'
#218474
0'
#218787
b10000 2
1'
#219100
0'
#219413
b10001 2
1'
#219726
0'
#220039
b10010 2
1'
#220352
0'
#220665
b10011 2
1'
#220978
0'
#221291
b10100 2
1'
#221604
0'
#221917
b10101 2
1'
#222230
0'
#222543
b10110 2
1'
#222856
0'
#223169
b10111 2
1'
#223482
0'
#223795
b11000 2
1'
#224108
0'
#224421
b11001 2
1'
#224734
0'
#225047
b11010 2
1'
#225360
0'
#225673
b11011 2
1'
#225986
0'
#226299
b11100 2
1'
#226612
0'
#226925
b11101 2
1'
#227238
0'
#227551
b11110 2
1'
#227864
0'
#228177
b11111 2
1'
#228490
0'
#228803
b100000 2
1'
#229116
0'
#229429
b100001 2
1'
#229742
0'
#230055
b100010 2
1'
#230368
0'
#230681
b100011 2
1'
#230994
0'
#231307
b100100 2
1'
#231620
0'
#231933
b100101 2
1'
#232246
0'
#232559
b100110 2
1'
#232872
0'
#233185
b100111 2
1'
#233498
0'
#233811
b101000 2
1'
#234124
0'
#234437
b101001 2
1'
#234750
0'
#235063
b101010 2
1'
#235376
0'
#235689
b101011 2
1'
#236002
0'
#236315
b101100 2
1'
#236628
0'
#236941
b101101 2
1'
#237254
0'
#237567
b101110 2
1'
#237880
0'
#238193
b101111 2
1'
#238506
0'
#238819
b110000 2
1'
#239132
0'
#239445
b110001 2
1'
#239758
0'
#240071
b110010 2
1'
#240384
0'
#240697
b110011 2
1'
#241010
0'
#241323
b110100 2
1'
#241636
0'
#241949
b110101 2
1'
#242262
0'
#242575
b110110 2
1'
#242888
0'
#243201
b110111 2
1'
#243514
0'
#243827
b111000 2
1'
#244140
0'
#244453
b111001 2
1'
#244766
0'
#245079
b111010 2
1'
#245392
0'
#245705
b111011 2
1'
#246018
0'
#246331
b111100 2
1'
#246644
0'
#246957
b111101 2
1'
#247270
0'
#247583
b111110 2
1'
#247896
0'
#248209
b111111 2
1'
#248522
0'
#248835
b1000000 2
1'
#249148
0'
#249461
b1000001 2
1'
#249774
0'
#250087
b1000010 2
1'
#250400
0'
#250713
b1000011 2
1'
#251026
0'
#251339
b1000100 2
1'
#251652
0'
#251965
b1000101 2
1'
#252278
0'
#252591
b1000110 2
1'
#252904
0'
#253217
b1000111 2
1'
#253530
0'
#253843
b1001000 2
1'
#254156
0'
#254469
b1001001 2
1'
#254782
0'
#255095
b1001010 2
1'
#255408
0'
#255721
b1001011 2
1'
#256034
0'
#256347
b1001100 2
1'
#256660
0'
#256973
b1001101 2
1'
#257286
0'
#257599
b1001110 2
1'
#257912
0'
#258225
b1001111 2
1'
#258538
0'
#258851
b1010000 2
1'
#259164
0'
#259477
b1010001 2
1'
#259790
0'
#260103
b1010010 2
1'
#260416
0'
#260729
b1010011 2
1'
#261042
0'
#261355
b1010100 2
1'
#261668
0'
#261981
b1010101 2
1'
#262294
0'
#262607
b1010110 2
1'
#262920
0'
#263233
b1010111 2
1'
#263546
0'
#263859
b1011000 2
1'
#264172
0'
#264485
b1011001 2
1'
#264798
0'
#265111
b1011010 2
1'
#265424
0'
#265737
b1011011 2
1'
#266050
0'
#266363
b1011100 2
1'
#266676
0'
#266989
b1011101 2
1'
#267302
0'
#267615
b1011110 2
1'
#267928
0'
#268241
b1011111 2
1'
#268554
0'
#268867
b1100000 2
1'
#269180
0'
#269493
b1100001 2
1'
#269806
0'
#270119
b1100010 2
1'
#270432
0'
#270745
b1100011 2
1'
#271058
0'
#271371
b1100100 2
1'
#271684
0'
#271997
b1100101 2
1'
#272310
0'
#272623
b1100110 2
1'
#272936
0'
#273249
b1100111 2
1'
#273562
0'
#273875
b1101000 2
1'
#274188
0'
#274501
b1101001 2
1'
#274814
0'
#275127
b1101010 2
1'
#275440
0'
#275753
b1101011 2
1'
#276066
0'
#276379
b1101100 2
1'
#276692
0'
#277005
b1101101 2
1'
#277318
0'
#277631
b1101110 2
1'
#277944
0'
#278257
b1101111 2
1'
#278570
0'
#278883
b1110000 2
1'
#279196
0'
#279509
b1110001 2
1'
#279822
0'
#280135
b1110010 2
1'
#280448
0'
#280761
b1110011 2
1'
#281074
0'
#281387
b1110100 2
1'
#281700
0'
#282013
b1110101 2
1'
#282326
0'
#282639
b1110110 2
1'
#282952
0'
#283265
b1110111 2
1'
#283578
0'
#283891
b1111000 2
1'
#284204
0'
#284517
b1111001 2
1'
#284830
0'
#285143
b1111010 2
1'
#285456
0'
#285769
b1111011 2
1'
#286082
0'
#286395
b1111100 2
1'
#286708
0'
#287021
b1111101 2
1'
#287334
0'
#287647
b1111110 2
1'
#287960
0'
#288273
b1111111 2
1'
#288586
0'
#288899
b10000000 2
1'
#289212
0'
#289525
b10000001 2
1'
#289838
0'
#290151
b10000010 2
1'
#290464
0'
#290777
b10000011 2
1'
#291090
0'
#291403
b10000100 2
1'
#291716
0'
#292029
b10000101 2
1'
#292342
0'
#292655
b10000110 2
1'
#292968
0'
#293281
b10000111 2
1'
#293594
0'
#293907
b10001000 2
1'
#294220
0'
#294533
b10001001 2
1'
#294846
0'
#295159
b10001010 2
1'
#295472
0'
#295785
b10001011 2
1'
#296098
0'
#296411
b10001100 2
1'
#296724
0'
#297037
b10001101 2
1'
#297350
0'
#297663
b10001110 2
1'
#297976
0'
#298289
b10001111 2
1'
#298602
0'
#298915
b10010000 2
1'
#299228
0'
#299541
b10010001 2
1'
#299854
0'
#300167
b10010010 2
1'
#300480
0'
#300793
b10010011 2
1'
#301106
0'
#301419
b10010100 2
1'
#301732
0'
#302045
b10010101 2
1'
#302358
0'
#302671
b10010110 2
1'
#302984
0'
#303297
b10010111 2
1'
#303610
0'
#303923
b10011000 2
1'
#304236
0'
#304549
b10011001 2
1'
#304862
0'
#305175
b10011010 2
1'
#305488
0'
#305801
b10011011 2
1'
#306114
0'
#306427
b10011100 2
1'
#306740
0'
#307053
b10011101 2
1'
#307366
0'
#307679
b10011110 2
1'
#307992
0'
#308305
b10011111 2
1'
#308618
0'
#308931
b10100000 2
1'
#309244
0'
#309557
b10100001 2
1'
#309870
0'
#310183
b10100010 2
1'
#310496
0'
#310809
b10100011 2
1'
#311122
0'
#311435
b10100100 2
1'
#311748
0'
#312061
b10100101 2
1'
#312374
0'
#312687
b10100110 2
1'
#313000
0'
#313313
b10100111 2
1'
#313626
0'
#313939
b10101000 2
1'
#314252
0'
#314565
b10101001 2
1'
#314878
0'
#315191
b10101010 2
1'
#315504
0'
#315817
b10101011 2
1'
#316130
0'
#316443
b10101100 2
1'
#316756
0'
#317069
b10101101 2
1'
#317382
0'
#317695
b10101110 2
1'
#318008
0'
#318321
b10101111 2
1'
#318634
0'
#318947
b10110000 2
1'
#319260
0'
#319573
b10110001 2
1'
#319886
0'
#320199
b10110010 2
1'
#320512
0'
#320825
b10110011 2
1'
#321138
0'
#321451
b10110100 2
1'
#321764
0'
#322077
b10110101 2
1'
#322390
0'
#322703
b10110110 2
1'
#323016
0'
#323329
b10110111 2
1'
#323642
0'
#323955
b10111000 2
1'
#324268
0'
#324581
b10111001 2
1'
#324894
0'
#325207
b10111010 2
1'
#325520
0'
#325833
b10111011 2
1'
#326146
0'
#326459
b10111100 2
1'
#326772
0'
#327085
b10111101 2
1'
#327398
0'
#327711
b10111110 2
1'
#328024
0'
#328337
b10111111 2
1'
#328650
0'
#328963
b11000000 2
1'
#329276
0'
#329589
b11000001 2
1'
#329902
0'
#330215
b11000010 2
1'
#330528
0'
#330841
b11000011 2
1'
#331154
0'
#331467
b11000100 2
1'
#331780
0'
#332093
b11000101 2
1'
#332406
0'
#332719
b11000110 2
1'
#333032
0'
#333345
b11000111 2
1'
#333658
0'
#333971
b11001000 2
1'
#334284
0'
#334597
b11001001 2
1'
#334910
0'
#335223
b11001010 2
1'
#335536
0'
#335849
b11001011 2
1'
#336162
0'
#336475
b11001100 2
1'
#336788
0'
#337101
b11001101 2
1'
#337414
0'
#337727
b11001110 2
1'
#338040
0'
#338353
b11001111 2
1'
#338666
0'
#338979
b11010000 2
1'
#339292
0'
#339605
b11010001 2
1'
#339918
0'
#340231
b11010010 2
1'
#340544
0'
#340857
b11010011 2
1'
#341170
0'
#341483
b11010100 2
1'
#341796
0'
#342109
b11010101 2
1'
#342422
0'
#342735
b11010110 2
1'
#343048
0'
#343361
b11010111 2
1'
#343674
0'
#343987
b11011000 2
1'
#344300
0'
#344613
b11011001 2
1'
#344926
0'
#345239
b11011010 2
1'
#345552
0'
#345865
b11011011 2
1'
#346178
0'
#346491
b11011100 2
1'
#346804
0'
#347117
b11011101 2
1'
#347430
0'
#347743
b11011110 2
1'
#348056
0'
#348369
b11011111 2
1'
#348682
0'
#348995
b11100000 2
1'
#349308
0'
#349621
b11100001 2
1'
#349934
0'
#350247
b11100010 2
1'
#350560
0'
#350873
b11100011 2
1'
#351186
0'
#351499
b11100100 2
1'
#351812
0'
#352125
b11100101 2
1'
#352438
0'
#352751
b11100110 2
1'
#353064
0'
#353377
b11100111 2
1'
#353690
0'
#354003
b11101000 2
1'
#354316
0'
#354629
b11101001 2
1'
#354942
0'
#355255
b11101010 2
1'
#355568
0'
#355881
b11101011 2
1'
#356194
0'
#356507
b11101100 2
1'
#356820
0'
#357133
b11101101 2
1'
#357446
0'
#357759
b11101110 2
1'
#358072
0'
