hw/main_unit/adc_capture.v
module adc_capture (
  output reg adc_convst,
  output reg adc_sck,
  output reg adc_sdi,
  input   adc_sdo,

  input          clk, // 160MHz, 6.25 ns
  output reg [11:0] adc_ram_addr,
  input   [31:0] adc_ram_rd_data,
  output         adc_ram_we,
  output reg [31:0] adc_ram_wr_data,

  input   [31:0] adc_config_odd,
  input   [31:0] adc_config_even,
  input adc_start,
  input adc_sequence_one
);

//wire [5:0] adc_config [0:1];
//assign adc_config[0][5:0] = adc_config_even[5:0];
//assign adc_config[1][5:0] = adc_config_odd[5:0];
wire [5:0] adc_config;
assign adc_config = ( adc_ram_addr[0] == 1'b1 ) ? adc_config_odd[5:0] : adc_config_even[5:0];
wire start_t_cyc;
assign start_t_cyc = adc_start;
                // tCYC    | Total Cycle Time | 2 μs       (320) /0001 0100 0000/
wire t_wh_conv; // tWHCONV | CONVST High Time | min 20 ns    (4) /0000 0000 0100/
wire t_conv;    // tCONV   | Conversion Time  | max 1.6 μs (256) /0001 0000 0000/

reg [8:0] t_cyc_counter;
always @(posedge clk) begin
  if (start_t_cyc || (t_cyc_counter == 9'd319))
    t_cyc_counter <= 9'b0;
  else
    t_cyc_counter <= t_cyc_counter + 1'b1;
end

always @(posedge clk) begin
  if (start_t_cyc)
    adc_ram_addr <= 9'b0;
  else if (t_cyc_counter == 8'd1)
    adc_ram_addr <= adc_ram_addr + 1'b1;
end

// adc_convst
/* A rising edge at CONVST begins a conversion. For best performance,
ensure that CONVST returns low within 40ns after the conversion starts
or after the conversion ends.*/
always @(posedge clk) begin
  if (t_cyc_counter == 8'd1)
    adc_convst <= 1'b1;
  else if (t_cyc_counter == 8'd7)
    adc_convst <= 1'b0;
end

// adc_sck
always @(posedge clk) begin
  if ((t_cyc_counter[8] == 1'b1) && (t_cyc_counter[7:2] < 6'd12))
    adc_sck <= t_cyc_counter[1];
  else
    adc_sck <= 1'b0;
end

// adc_sdi
always @(posedge clk) begin
  if ((t_cyc_counter[8] == 1'b1) && (t_cyc_counter[7:2] < 6'd6))
    //adc_sdi = adc_config[adc_ram_addr[0]][t_cyc_counter[4:2]];
    adc_sdi <= adc_config[6'd5 - t_cyc_counter[4:2]];
  else
    adc_sdi <= 1'b0;
end

// adc_sdo
reg [11:0] adc_data;
always @(posedge clk) begin
  if ((t_cyc_counter[8] == 1'b1) && (t_cyc_counter[7:2] < 6'd13) && (t_cyc_counter[1:0] == 2'b0))
    adc_data <= {adc_data[10:0],adc_sdo};
end

// wr mem
reg [31:0] adc_ram_rd_data_reg;
always @(posedge clk) begin
  if (t_cyc_counter == 9'd315)
    adc_ram_rd_data_reg <= adc_ram_rd_data;
end
always @(posedge clk) begin
  if (t_cyc_counter == 9'd316)
    adc_ram_wr_data <= adc_ram_rd_data_reg + adc_data;
end
assign adc_ram_we = t_cyc_counter == 9'd317;

endmodule

hw/tb/main_unit__adc_capture__tb.v
// iverilog -y ../main_unit -o adc_capture main_unit__adc_capture__tb.v
// vvp adc_capture
// gtkwave -f main_unit__adc_capture__tb.vcd
`timescale 1 ns / 10 ps

module main_unit__adc_capture__tb;

parameter PERIOD = 6.25; // 160MHz -> 6.25ns
parameter DO_CYCLES = 320*3;

wire adc_convst;
wire adc_sck;
wire adc_sdi;
reg adc_sdo = 1'b1;
reg clk;

wire [11:0] adc_ram_addr;
reg [31:0] adc_ram_rd_data = 32'h1234;
wire adc_ram_we;
wire [31:0] adc_ram_wr_data;

reg [31:0] adc_config_odd = 32'b101010;
reg [31:0] adc_config_even = 32'b010101;
reg adc_start = 1'b1;
reg adc_sequence_one = 1'b0;


adc_capture adc_capture (
  .adc_convst(adc_convst),//output  adc_convst,
  .adc_sck(adc_sck),//output  adc_sck,
  .adc_sdi(adc_sdi),//output  adc_sdi,
  .adc_sdo(adc_sdo),//input   adc_sdo,

  .clk(clk),//input          clk,
  .adc_ram_addr(adc_ram_addr),//output  [11:0] adc_ram_addr,
  .adc_ram_rd_data(adc_ram_rd_data),//input   [31:0] adc_ram_rd_data,
  .adc_ram_we(adc_ram_we),//output         adc_ram_we,
  .adc_ram_wr_data(adc_ram_wr_data),//output  [31:0] adc_ram_wr_data,

  .adc_config_odd(adc_config_odd),//input   [31:0] adc_config_odd,
  .adc_config_even(adc_config_even),//input   [31:0] adc_config_even,
  .adc_start(adc_start),//input adc_start
  .adc_sequence_one(adc_sequence_one)//input adc_sequence_one
);

initial begin
  $dumpfile("main_unit__adc_capture__tb.vcd");
  $dumpvars(0, adc_capture);
end

initial begin
  clk = 0;
  forever #(PERIOD/2) clk = ~clk;
end

initial begin
  adc_start = 1'b1;
  #(PERIOD*13);
  adc_start = 1'b0;
  repeat (DO_CYCLES) @(negedge clk);
  $finish;
end

endmodule

hw/tb/main_unit__adc_capture__tb.vcd
$date
	Sun Jan 16 23:14:11 2022
$end
$version
	Icarus Verilog
$end
$timescale
	1ps
$end
$scope module main_unit__adc_capture__tb $end
$var wire 1 ! adc_convst $end
$upscope $end
$scope module main_unit__adc_capture__tb $end
$var wire 1 " adc_sck $end
$upscope $end
$scope module main_unit__adc_capture__tb $end
$var wire 1 # adc_sdi $end
$upscope $end
$scope module main_unit__adc_capture__tb $end
$var wire 1 $ adc_sdo $end
$upscope $end
$scope module main_unit__adc_capture__tb $end
$var reg 1 % clk $end
$upscope $end
$scope module main_unit__adc_capture__tb $end
$var wire 12 & adc_ram_addr [11:0] $end
$upscope $end
$scope module main_unit__adc_capture__tb $end
$var reg 32 ' adc_ram_rd_data [31:0] $end
$upscope $end
$scope module main_unit__adc_capture__tb $end
$var wire 1 ( adc_ram_we $end
$upscope $end
$scope module main_unit__adc_capture__tb $end
$var wire 32 ) adc_ram_wr_data [31:0] $end
$upscope $end
$scope module main_unit__adc_capture__tb $end
$var reg 32 * adc_config_odd [31:0] $end
$upscope $end
$scope module main_unit__adc_capture__tb $end
$var reg 32 + adc_config_even [31:0] $end
$upscope $end
$scope module main_unit__adc_capture__tb $end
$var reg 1 , adc_start $end
$upscope $end
$scope module main_unit__adc_capture__tb $end
$var reg 1 - adc_sequence_one $end
$upscope $end
$enddefinitions $end
#0
$dumpvars
0-
1,
b10101 +
b101010 *
bx )
x(
b1001000110100 '
bx &
0%
0$
x#
x"
x!
$end
#3125
0(
b0 &
0"
0#
1%
#6250
0%
#9375
1%
#12500
0%
#15625
1%
#18750
0%
#21875
1%
#25000
0%
#28125
1%
#31250
0%
#34375
1%
#37500
0%
#40625
1%
#43750
0%
#46875
1%
#50000
0%
#53125
1%
#56250
0%
#59375
1%
#62500
0%
#65625
1%
#68750
0%
#71875
1%
#75000
0%
#78125
1%
#81250
0%
0,
#84375
1%
#87500
0%
#90625
b1 &
1!
1%
#93750
0%
#96875
1%
#100000
0%
#103125
1%
#106250
0%
#109375
1%
#112500
0%
#115625
1%
#118750
0%
#121875
1%
#125000
0%
#128125
0!
1%
#131250
0%
#134375
1%
#137500
0%
#140625
1%
#143750
0%
#146875
1%
#150000
0%
#153125
1%
#156250
0%
#159375
1%
#162500
0%
#165625
1%
#168750
0%
#171875
1%
#175000
0%
#178125
1%
#181250
0%
#184375
1%
#187500
0%
#190625
1%
#193750
0%
#196875
1%
#200000
0%
#203125
1%
#206250
0%
#209375
1%
#212500
0%
#215625
1%
#218750
0%
#221875
1%
#225000
0%
#228125
1%
#231250
0%
#234375
1%
#237500
0%
#240625
1%
#243750
0%
#246875
1%
#250000
0%
#253125
1%
#256250
0%
#259375
1%
#262500
0%
#265625
1%
#268750
0%
#271875
1%
#275000
0%
#278125
1%
#281250
0%
#284375
1%
#287500
0%
#290625
1%
#293750
0%
#296875
1%
#300000
0%
#303125
1%
#306250
0%
#309375
1%
#312500
0%
#315625
1%
#318750
0%
#321875
1%
#325000
0%
#328125
1%
#331250
0%
#334375
1%
#337500
0%
#340625
1%
#343750
0%
#346875
1%
#350000
0%
#353125
1%
#356250
0%
#359375
1%
#362500
0%
#365625
1%
#368750
0%
#371875
1%
#375000
0%
#378125
1%
#381250
0%
#384375
1%
#387500
0%
#390625
1%
#393750
0%
#396875
1%
#400000
0%
#403125
1%
#406250
0%
#409375
1%
#412500
0%
#415625
1%
#418750
0%
#421875
1%
#425000
0%
#428125
1%
#431250
0%
#434375
1%
#437500
0%
#440625
1%
#443750
0%
#446875
1%
#450000
0%
#453125
1%
#456250
0%
#459375
1%
#462500
0%
#465625
1%
#468750
0%
#471875
1%
#475000
0%
#478125
1%
#481250
0%
#484375
1%
#487500
0%
#490625
1%
#493750
0%
#496875
1%
#500000
0%
#503125
1%
#506250
0%
#509375
1%
#512500
0%
#515625
1%
#518750
0%
#521875
1%
#525000
0%
#528125
1%
#531250
0%
#534375
1%
#537500
0%
#540625
1%
#543750
0%
#546875
1%
#550000
0%
#553125
1%
#556250
0%
#559375
1%
#562500
0%
#565625
1%
#568750
0%
#571875
1%
#575000
0%
#578125
1%
#581250
0%
#584375
1%
#587500
0%
#590625
1%
#593750
0%
#596875
1%
#600000
0%
#603125
1%
#606250
0%
#609375
1%
#612500
0%
#615625
1%
#618750
0%
#621875
1%
#625000
0%
#628125
1%
#631250
0%
#634375
1%
#637500
0%
#640625
1%
#643750
0%
#646875
1%
#650000
0%
#653125
1%
#656250
0%
#659375
1%
#662500
0%
#665625
1%
#668750
0%
#671875
1%
#675000
0%
#678125
1%
#681250
0%
#684375
1%
#687500
0%
#690625
1%
#693750
0%
#696875
1%
#700000
0%
#703125
1%
#706250
0%
#709375
1%
#712500
0%
#715625
1%
#718750
0%
#721875
1%
#725000
0%
#728125
1%
#731250
0%
#734375
1%
#737500
0%
#740625
1%
#743750
0%
#746875
1%
#750000
0%
#753125
1%
#756250
0%
#759375
1%
#762500
0%
#765625
1%
#768750
0%
#771875
1%
#775000
0%
#778125
1%
#781250
0%
#784375
1%
#787500
0%
#790625
1%
#793750
0%
#796875
1%
#800000
0%
#803125
1%
#806250
0%
#809375
1%
#812500
0%
#815625
1%
#818750
0%
#821875
1%
#825000
0%
#828125
1%
#831250
0%
#834375
1%
#837500
0%
#840625
1%
#843750
0%
#846875
1%
#850000
0%
#853125
1%
#856250
0%
#859375
1%
#862500
0%
#865625
1%
#868750
0%
#871875
1%
#875000
0%
#878125
1%
#881250
0%
#884375
1%
#887500
0%
#890625
1%
#893750
0%
#896875
1%
#900000
0%
#903125
1%
#906250
0%
#909375
1%
#912500
0%
#915625
1%
#918750
0%
#921875
1%
#925000
0%
#928125
1%
#931250
0%
#934375
1%
#937500
0%
#940625
1%
#943750
0%
#946875
1%
#950000
0%
#953125
1%
#956250
0%
#959375
1%
#962500
0%
#965625
1%
#968750
0%
#971875
1%
#975000
0%
#978125
1%
#981250
0%
#984375
1%
#987500
0%
#990625
1%
#993750
0%
#996875
1%
#1000000
0%
#1003125
1%
#1006250
0%
#1009375
1%
#1012500
0%
#1015625
1%
#1018750
0%
#1021875
1%
#1025000
0%
#1028125
1%
#1031250
0%
#1034375
1%
#1037500
0%
#1040625
1%
#1043750
0%
#1046875
1%
#1050000
0%
#1053125
1%
#1056250
0%
#1059375
1%
#1062500
0%
#1065625
1%
#1068750
0%
#1071875
1%
#1075000
0%
#1078125
1%
#1081250
0%
#1084375
1%
#1087500
0%
#1090625
1%
#1093750
0%
#1096875
1%
#1100000
0%
#1103125
1%
#1106250
0%
#1109375
1%
#1112500
0%
#1115625
1%
#1118750
0%
#1121875
1%
#1125000
0%
#1128125
1%
#1131250
0%
#1134375
1%
#1137500
0%
#1140625
1%
#1143750
0%
#1146875
1%
#1150000
0%
#1153125
1%
#1156250
0%
#1159375
1%
#1162500
0%
#1165625
1%
#1168750
0%
#1171875
1%
#1175000
0%
#1178125
1%
#1181250
0%
#1184375
1%
#1187500
0%
#1190625
1%
#1193750
0%
#1196875
1%
#1200000
0%
#1203125
1%
#1206250
0%
#1209375
1%
#1212500
0%
#1215625
1%
#1218750
0%
#1221875
1%
#1225000
0%
#1228125
1%
#1231250
0%
#1234375
1%
#1237500
0%
#1240625
1%
#1243750
0%
#1246875
1%
#1250000
0%
#1253125
1%
#1256250
0%
#1259375
1%
#1262500
0%
#1265625
1%
#1268750
0%
#1271875
1%
#1275000
0%
#1278125
1%
#1281250
0%
#1284375
1%
#1287500
0%
#1290625
1%
#1293750
0%
#1296875
1%
#1300000
0%
#1303125
1%
#1306250
0%
#1309375
1%
#1312500
0%
#1315625
1%
#1318750
0%
#1321875
1%
#1325000
0%
#1328125
1%
#1331250
0%
#1334375
1%
#1337500
0%
#1340625
1%
#1343750
0%
#1346875
1%
#1350000
0%
#1353125
1%
#1356250
0%
#1359375
1%
#1362500
0%
#1365625
1%
#1368750
0%
#1371875
1%
#1375000
0%
#1378125
1%
#1381250
0%
#1384375
1%
#1387500
0%
#1390625
1%
#1393750
0%
#1396875
1%
#1400000
0%
#1403125
1%
#1406250
0%
#1409375
1%
#1412500
0%
#1415625
1%
#1418750
0%
#1421875
1%
#1425000
0%
#1428125
1%
#1431250
0%
#1434375
1%
#1437500
0%
#1440625
1%
#1443750
0%
#1446875
1%
#1450000
0%
#1453125
1%
#1456250
0%
#1459375
1%
#1462500
0%
#1465625
1%
#1468750
0%
#1471875
1%
#1475000
0%
#1478125
1%
#1481250
0%
#1484375
1%
#1487500
0%
#1490625
1%
#1493750
0%
#1496875
1%
#1500000
0%
#1503125
1%
#1506250
0%
#1509375
1%
#1512500
0%
#1515625
1%
#1518750
0%
#1521875
1%
#1525000
0%
#1528125
1%
#1531250
0%
#1534375
1%
#1537500
0%
#1540625
1%
#1543750
0%
#1546875
1%
#1550000
0%
#1553125
1%
#1556250
0%
#1559375
1%
#1562500
0%
#1565625
1%
#1568750
0%
#1571875
1%
#1575000
0%
#1578125
1%
#1581250
0%
#1584375
1%
#1587500
0%
#1590625
1%
#1593750
0%
#1596875
1%
#1600000
0%
#1603125
1%
#1606250
0%
#1609375
1%
#1612500
0%
#1615625
1%
#1618750
0%
#1621875
1%
#1625000
0%
#1628125
1%
#1631250
0%
#1634375
1%
#1637500
0%
#1640625
1%
#1643750
0%
#1646875
1%
#1650000
0%
#1653125
1%
#1656250
0%
#1659375
1%
#1662500
0%
#1665625
1%
#1668750
0%
#1671875
1%
#1675000
0%
#1678125
1%
#1681250
0%
#1684375
1%
#1687500
0%
#1690625
1%
#1693750
0%
#1696875
1$
1"
1%
#1700000
0%
#1703125
1%
#1706250
0%
#1709375
1#
0"
1%
#1712500
0%
#1715625
1%
#1718750
0%
#1721875
1"
1%
#1725000
0%
#1728125
1%
#1731250
0%
#1734375
0#
0"
1%
#1737500
0%
#1740625
1%
#1743750
0%
#1746875
0$
1"
1%
#1750000
0%
#1753125
1%
#1756250
0%
#1759375
1#
0"
1%
#1762500
0%
#1765625
1%
#1768750
0%
#1771875
1$
1"
1%
#1775000
0%
#1778125
1%
#1781250
0%
#1784375
0#
0"
1%
#1787500
0%
#1790625
1%
#1793750
0%
#1796875
0$
1"
1%
#1800000
0%
#1803125
1%
#1806250
0%
#1809375
1#
0"
1%
#1812500
0%
#1815625
1%
#1818750
0%
#1821875
1"
1%
#1825000
0%
#1828125
1%
#1831250
0%
#1834375
0#
0"
1%
#1837500
0%
#1840625
1%
#1843750
0%
#1846875
1"
1%
#1850000
0%
#1853125
1%
#1856250
0%
#1859375
0"
1%
#1862500
0%
#1865625
1%
#1868750
0%
#1871875
1"
1%
#1875000
0%
#1878125
1%
#1881250
0%
#1884375
0"
1%
#1887500
0%
#1890625
1%
#1893750
0%
#1896875
1"
1%
#1900000
0%
#1903125
1%
#1906250
0%
#1909375
0"
1%
#1912500
0%
#1915625
1%
#1918750
0%
#1921875
1"
1%
#1925000
0%
#1928125
1%
#1931250
0%
#1934375
0"
1%
#1937500
0%
#1940625
1%
#1943750
0%
#1946875
1"
1%
#1950000
0%
#1953125
1%
#1956250
0%
#1959375
0"
1%
#1962500
0%
#1965625
1%
#1968750
0%
#1971875
1"
1%
#1975000
0%
#1978125
1%
#1981250
0%
#1984375
0"
1%
#1987500
0%
#1990625
1%
#1993750
0%
#1996875
1%
#2000000
0%
#2003125
1%
#2006250
0%
#2009375
1%
#2012500
0%
#2015625
1%
#2018750
0%
#2021875
1%
#2025000
0%
#2028125
1%
#2031250
0%
#2034375
1%
#2037500
0%
#2040625
1%
#2043750
0%
#2046875
1%
#2050000
0%
#2053125
1%
#2056250
0%
#2059375
b1100010110100 )
1(
1%
#2062500
0%
#2065625
0(
1%
#2068750
0%
#2071875
1%
#2075000
0%
#2078125
1%
#2081250
0%
#2084375
1%
#2087500
0%
#2090625
b10 &
1!
1%
#2093750
0%
#2096875
1%
#2100000
0%
#2103125
1%
#2106250
0%
#2109375
1%
#2112500
0%
#2115625
1%
#2118750
0%
#2121875
1%
#2125000
0%
#2128125
0!
1%
